flask_pycasbin/__about__.py
flask_pycasbin/__init__.py
flask_pycasbin/utils.py
flask_pycasbin-0.0.1.dist-info/METADATA
flask_pycasbin-0.0.1.dist-info/WHEEL
flask_pycasbin-0.0.1.dist-info/top_level.txt
flask_pycasbin-0.0.1.dist-info/RECORD
