Metadata-Version: 2.1
Name: flask-pycasbin
Version: 0.0.1
Summary: A Flask extension integrating pycasbin
Home-page: https://github.com/BbsonLin/flask-pycasbin
Author: Bobson Lin
Author-email: bobson801104@gmail.com
License: MIT
Keywords: flask casbin pycasbin
Platform: UNKNOWN
Classifier: Development Status :: 1 - Planning
Classifier: Environment :: Web Environment
Classifier: Framework :: Flask
Classifier: Operating System :: OS Independent
Classifier: Intended Audience :: Developers
Classifier: Programming Language :: Python
Classifier: Programming Language :: Python :: 3
Classifier: Programming Language :: Python :: 3.5
Classifier: Programming Language :: Python :: 3.6
Classifier: Programming Language :: Python :: 3.7
Classifier: Programming Language :: Python :: Implementation :: PyPy
Classifier: Topic :: Software Development :: Libraries :: Python Modules
Classifier: License :: OSI Approved :: MIT License
Requires-Dist: flask
Requires-Dist: casbin
